[
    {
        "description": "Hello! Project Year End Party 2021 - 平山遊季 (No.1)",
        "image": "202112-YEP-01.jpg"
    },
    {
        "description": "Hello! Project Year End Party 2021 - 平山遊季 (No.2)",
        "image": "202112-YEP-02.jpg"
    },
    {
        "description": "Hello! Project Year End Party 2021 - 平山遊季 (No.3)",
        "image": "202112-YEP-03.jpg"
    },
    {
        "description": "Hello! Project Year End Party 2021 - 平山遊季 (No.4)",
        "image": "202112-YEP-04.jpg"
    },
    {
        "description": "Hello! Project Year End Party 2021 - 平山遊季 (No.5)",
        "image": "202112-YEP-05.jpg"
    },
    {
        "description": "Hello! Project Year End Party 2021 - 平山遊季 (No.6)",
        "image": "202112-YEP-06.jpg"
    },
    {
        "description": "Hello! Project Year End Party 2021 - 平山遊季 (No.7)",
        "image": "202112-YEP-07.jpg"
    },
    {
        "description": "Hello! Project Year End Party 2021 - 平山遊季 (No.8)",
        "image": "202112-YEP-08.jpg"
    }
]